{
  "timestamp": "2026-05-26T20:51:04.983380+00:00",
  "date": "2026-05-26",
  "summary": {
    "news": {
      "articles_found": 0,
      "high_relevance": 0,
      "top_headlines": []
    },
    "trump": {
      "mentions_found": 0,
      "market_moving": 0,
      "key_statements": []
    },
    "reddit": {
      "tickers_tracked": 0,
      "top_hype": [],
      "bullish_count": 0,
      "bearish_count": 0
    },
    "x": {
      "tickers_with_mentions": 0,
      "top_momentum": [
        "SCCO",
        "CRWD",
        "ETHW",
        "YB",
        "XRP"
      ],
      "bullish_count": 0,
      "bearish_count": 0
    },
    "volume": {
      "anomalies_found": 4,
      "top_signals": [
        "BIVI",
        "WCT",
        "ROBO",
        "MEME"
      ]
    }
  },
  "alerts": [],
  "watchlist_adds": [],
  "sector_rotation": {},
  "macro_context": {
    "vix": {
      "level": 0,
      "change_pct": 0
    },
    "yield_10y": {
      "yield": 0
    },
    "dxy": {
      "level": 0,
      "change_pct": 0
    },
    "regime": "RISK_ON",
    "risk_level": "MEDIUM"
  },
  "actions": [
    "Check 4 volume anomalies"
  ]
}